[
 {
   "FIELD1": "Área Metropolitana do Porto",
   "FIELD2": "Área Metropolitana do Porto",
   "FIELD3": "1.595.762",
   "FIELD4": "1.730.845",
   "FIELD5": "1.759.524",
   "FIELD6": "1.737.395"
 },
 {
   "FIELD1": "Arouca",
   "FIELD2": "Concelho",
   "FIELD3": "23.894",
   "FIELD4": "24.227",
   "FIELD5": "22.359",
   "FIELD6": "21.154"
 },
 {
   "FIELD1": " ",
   "FIELD2": "Alvarenga",
   "FIELD3": "1.637",
   "FIELD4": "1.368",
   "FIELD5": "1.223",
   "FIELD6": "1.057"
 },
 {
   "FIELD1": "Chave",
   "FIELD2": "1.398",
   "FIELD3": "1.414",
   "FIELD4": "1.253",
   "FIELD5": "1.270",
   "FIELD6": ""
 },
 {
   "FIELD1": "Escariz",
   "FIELD2": "2.055",
   "FIELD3": "2.255",
   "FIELD4": "2.222",
   "FIELD5": "2.114",
   "FIELD6": ""
 },
 {
   "FIELD1": "Fermedo",
   "FIELD2": "1.552",
   "FIELD3": "1.504",
   "FIELD4": "1.340",
   "FIELD5": "1.261",
   "FIELD6": ""
 },
 {
   "FIELD1": "Mansores",
   "FIELD2": "1.125",
   "FIELD3": "1.155",
   "FIELD4": "1.081",
   "FIELD5": "1.100",
   "FIELD6": ""
 },
 {
   "FIELD1": "Moldes",
   "FIELD2": "1.596",
   "FIELD3": "1.477",
   "FIELD4": "1.257",
   "FIELD5": "1.126",
   "FIELD6": ""
 },
 {
   "FIELD1": "Rossas",
   "FIELD2": "1.527",
   "FIELD3": "1.693",
   "FIELD4": "1.599",
   "FIELD5": "1.491",
   "FIELD6": ""
 },
 {
   "FIELD1": "Santa Eulália",
   "FIELD2": "2.132",
   "FIELD3": "2.339",
   "FIELD4": "2.253",
   "FIELD5": "2.120",
   "FIELD6": ""
 },
 {
   "FIELD1": "São Miguel do Mato",
   "FIELD2": "851",
   "FIELD3": "800",
   "FIELD4": "598",
   "FIELD5": "550",
   "FIELD6": ""
 },
 {
   "FIELD1": "Tropeço",
   "FIELD2": "1.277",
   "FIELD3": "1.297",
   "FIELD4": "1.150",
   "FIELD5": "1.086",
   "FIELD6": ""
 },
 {
   "FIELD1": "U.F. de Arouca e Burgo",
   "FIELD2": "",
   "FIELD3": "",
   "FIELD4": "5.178",
   "FIELD5": "5.124",
   "FIELD6": ""
 },
 {
   "FIELD1": "U.F. de Cabreiros e Albergaria da Serra",
   "FIELD2": "",
   "FIELD3": "",
   "FIELD4": "231",
   "FIELD5": "185",
   "FIELD6": ""
 },
 {
   "FIELD1": "U.F. de Canelas e Espiunca",
   "FIELD2": "",
   "FIELD3": "",
   "FIELD4": "1.183",
   "FIELD5": "1.065",
   "FIELD6": ""
 },
 {
   "FIELD1": "U.F. de Covelo de Paivó e Janarde",
   "FIELD2": "",
   "FIELD3": "",
   "FIELD4": "222",
   "FIELD5": "171",
   "FIELD6": ""
 },
 {
   "FIELD1": "Urrô",
   "FIELD2": "1.068",
   "FIELD3": "1.206",
   "FIELD4": "1.029",
   "FIELD5": "900",
   "FIELD6": ""
 },
 {
   "FIELD1": "Várzea",
   "FIELD2": "545",
   "FIELD3": "559",
   "FIELD4": "540",
   "FIELD5": "534",
   "FIELD6": ""
 },
 {
   "FIELD1": "Espinho",
   "FIELD2": "Concelho",
   "FIELD3": "34.956",
   "FIELD4": "33.701",
   "FIELD5": "31.786",
   "FIELD6": "31.045"
 },
 {
   "FIELD1": "",
   "FIELD2": "Espinho",
   "FIELD3": "11.888",
   "FIELD4": "10.225",
   "FIELD5": "9.832",
   "FIELD6": "10.434"
 },
 {
   "FIELD1": "Paramos",
   "FIELD2": "3.820",
   "FIELD3": "3.789",
   "FIELD4": "3.515",
   "FIELD5": "3.127",
   "FIELD6": ""
 },
 {
   "FIELD1": "Silvalde",
   "FIELD2": "8.180",
   "FIELD3": "7.540",
   "FIELD4": "6.673",
   "FIELD5": "6.108",
   "FIELD6": ""
 },
 {
   "FIELD1": "U.F. de Anta e Guetim",
   "FIELD2": "",
   "FIELD3": "",
   "FIELD4": "11.766",
   "FIELD5": "11.376",
   "FIELD6": ""
 },
 {
   "FIELD1": "Gondomar",
   "FIELD2": "Concelho",
   "FIELD3": "143.178",
   "FIELD4": "164.096",
   "FIELD5": "168.027",
   "FIELD6": "164.277"
 },
 {
   "FIELD1": "",
   "FIELD2": "Baguim do Monte (Rio Tinto)",
   "FIELD3": "9.651",
   "FIELD4": "13.943",
   "FIELD5": "14.102",
   "FIELD6": "14.387"
 },
 {
   "FIELD1": "Lomba",
   "FIELD2": "1.851",
   "FIELD3": "1.711",
   "FIELD4": "1.505",
   "FIELD5": "1.286",
   "FIELD6": ""
 },
 {
   "FIELD1": "Rio Tinto",
   "FIELD2": "40.907",
   "FIELD3": "47.695",
   "FIELD4": "50.713",
   "FIELD5": "51.086",
   "FIELD6": ""
 },
 {
   "FIELD1": "U.F. de Fânzeres e São Pedro da Cova",
   "FIELD2": "",
   "FIELD3": "",
   "FIELD4": "39.586",
   "FIELD5": "37.756",
   "FIELD6": ""
 },
 {
   "FIELD1": "U.F. de Foz do Sousa e Covelo",
   "FIELD2": "",
   "FIELD3": "",
   "FIELD4": "7.701",
   "FIELD5": "7.040",
   "FIELD6": ""
 },
 {
   "FIELD1": "U.F. de Gondomar (São Cosme), Valbom e Jovim",
   "FIELD2": "",
   "FIELD3": "",
   "FIELD4": "48.600",
   "FIELD5": "47.427",
   "FIELD6": ""
 },
 {
   "FIELD1": "U.F. de Melres e Medas",
   "FIELD2": "",
   "FIELD3": "",
   "FIELD4": "5.820",
   "FIELD5": "5.295",
   "FIELD6": ""
 },
 {
   "FIELD1": "Maia",
   "FIELD2": "Concelho",
   "FIELD3": "143.178",
   "FIELD4": "164.096",
   "FIELD5": "135.306",
   "FIELD6": "164.277"
 },
 {
   "FIELD1": "",
   "FIELD2": "Águas Santas",
   "FIELD3": "9.651",
   "FIELD4": "13.943",
   "FIELD5": "27.470",
   "FIELD6": "26.635"
 },
 {
   "FIELD1": "Castêlo da Maia",
   "FIELD2": "",
   "FIELD3": "",
   "FIELD4": "18.395",
   "FIELD5": "18.588",
   "FIELD6": ""
 },
 {
   "FIELD1": "Cidade da Maia",
   "FIELD2": "",
   "FIELD3": "",
   "FIELD4": "40.134",
   "FIELD5": "40.535",
   "FIELD6": ""
 },
 {
   "FIELD1": "Folgosa",
   "FIELD2": "",
   "FIELD3": "",
   "FIELD4": "3.704",
   "FIELD5": "3.605",
   "FIELD6": ""
 },
 {
   "FIELD1": "Milheirós",
   "FIELD2": "",
   "FIELD3": "",
   "FIELD4": "4.861",
   "FIELD5": "4.762",
   "FIELD6": ""
 },
 {
   "FIELD1": "Moreira",
   "FIELD2": "",
   "FIELD3": "",
   "FIELD4": "12.890",
   "FIELD5": "13.094",
   "FIELD6": ""
 },
 {
   "FIELD1": "Nogueira e Silva Escura",
   "FIELD2": "",
   "FIELD3": "",
   "FIELD4": "7.980",
   "FIELD5": "8.381",
   "FIELD6": ""
 },
 {
   "FIELD1": "Pedrouços",
   "FIELD2": "",
   "FIELD3": "",
   "FIELD4": "12.149",
   "FIELD5": "11.568",
   "FIELD6": ""
 },
 {
   "FIELD1": "São Pedro Fins",
   "FIELD2": "",
   "FIELD3": "",
   "FIELD4": "1.837",
   "FIELD5": "1.816",
   "FIELD6": ""
 },
 {
   "FIELD1": "Vila Nova da Telha",
   "FIELD2": "",
   "FIELD3": "",
   "FIELD4": "8.886",
   "FIELD5": "6.004",
   "FIELD6": ""
 },
 {
   "FIELD1": "Matosinhos",
   "FIELD2": "Concelho",
   "FIELD3": "151.682",
   "FIELD4": "167.026",
   "FIELD5": "175.478",
   "FIELD6": "172.586"
 },
 {
   "FIELD1": "",
   "FIELD2": "U.F de Custóias, Leça do Balio e Guifões",
   "FIELD3": "",
   "FIELD4": "",
   "FIELD5": "45.716",
   "FIELD6": "44.048"
 },
 {
   "FIELD1": "U.F de Matosinhos e Leça da Palmeira",
   "FIELD2": "",
   "FIELD3": "",
   "FIELD4": "49.486",
   "FIELD5": "49.046",
   "FIELD6": ""
 },
 {
   "FIELD1": "U.F de Perafita, Lavra e Santa Cruz do Bispo",
   "FIELD2": "",
   "FIELD3": "",
   "FIELD4": "29.407",
   "FIELD5": "29.653",
   "FIELD6": ""
 },
 {
   "FIELD1": "U.F de São Mamede de Infesta e Senhora da Hora",
   "FIELD2": "",
   "FIELD3": "",
   "FIELD4": "50.869",
   "FIELD5": "49.839",
   "FIELD6": ""
 },
 {
   "FIELD1": "Oliveira de Azeméis",
   "FIELD2": "Concelho",
   "FIELD3": "66.846",
   "FIELD4": "70.721",
   "FIELD5": "68.611",
   "FIELD6": "66.190"
 },
 {
   "FIELD1": "",
   "FIELD2": "Carregosa",
   "FIELD3": "3.544",
   "FIELD4": "3.552",
   "FIELD5": "3.419",
   "FIELD6": "3.466"
 },
 {
   "FIELD1": "Cesar",
   "FIELD2": "2.739",
   "FIELD3": "3.288",
   "FIELD4": "3.166",
   "FIELD5": "3.073",
   "FIELD6": ""
 },
 {
   "FIELD1": "Fajões",
   "FIELD2": "3.112",
   "FIELD3": "3.180",
   "FIELD4": "3.087",
   "FIELD5": "2.896",
   "FIELD6": ""
 },
 {
   "FIELD1": "Loureiro",
   "FIELD2": "3.376",
   "FIELD3": "3.491",
   "FIELD4": "3.531",
   "FIELD5": "3.638",
   "FIELD6": ""
 },
 {
   "FIELD1": "Macieira de Sarnes",
   "FIELD2": "2.193",
   "FIELD3": "2.214",
   "FIELD4": "1.925",
   "FIELD5": "1.856",
   "FIELD6": ""
 },
 {
   "FIELD1": "Ossela",
   "FIELD2": "2.359",
   "FIELD3": "2.538",
   "FIELD4": "2.208",
   "FIELD5": "1.918",
   "FIELD6": ""
 },
 {
   "FIELD1": "São Martinho da Gândara",
   "FIELD2": "2.237",
   "FIELD3": "2.289",
   "FIELD4": "1.985",
   "FIELD5": "1.854",
   "FIELD6": ""
 },
 {
   "FIELD1": "São Roque",
   "FIELD2": "5.156",
   "FIELD3": "5.480",
   "FIELD4": "5.228",
   "FIELD5": "5.025",
   "FIELD6": ""
 },
 {
   "FIELD1": "U.F. de Nogueira do Cravo e Pindelo",
   "FIELD2": "",
   "FIELD3": "",
   "FIELD4": "5.390",
   "FIELD5": "5.098",
   "FIELD6": ""
 },
 {
   "FIELD1": "U.F. de Oliveira de Azeméis, Santiago de Riba-Ul, Ul, Macinhata da Seixa e Madail",
   "FIELD2": "",
   "FIELD3": "",
   "FIELD4": "20.760",
   "FIELD5": "20.667",
   "FIELD6": ""
 },
 {
   "FIELD1": "U.F. de Pinheiro da Bemposta, Travanca e Palmaz",
   "FIELD2": "",
   "FIELD3": "",
   "FIELD4": "7.207",
   "FIELD5": "6.736",
   "FIELD6": ""
 },
 {
   "FIELD1": "Vila de Cucujães",
   "FIELD2": "11.130",
   "FIELD3": "11.094",
   "FIELD4": "10.705",
   "FIELD5": "9.963",
   "FIELD6": ""
 },
 {
   "FIELD1": "Paredes",
   "FIELD2": "Concelho",
   "FIELD3": "72.999",
   "FIELD4": "83.376",
   "FIELD5": "86.854",
   "FIELD6": "84.371"
 },
 {
   "FIELD1": "",
   "FIELD2": "Aguiar de Sousa",
   "FIELD3": "1.713",
   "FIELD4": "1.600",
   "FIELD5": "1.631",
   "FIELD6": "1.582"
 },
 {
   "FIELD1": "Astromil",
   "FIELD2": "728",
   "FIELD3": "784",
   "FIELD4": "1.086",
   "FIELD5": "1.067",
   "FIELD6": ""
 },
 {
   "FIELD1": "Baltar",
   "FIELD2": "4.023",
   "FIELD3": "4.666",
   "FIELD4": "4.818",
   "FIELD5": "4.724",
   "FIELD6": ""
 },
 {
   "FIELD1": "Beire",
   "FIELD2": "2.092",
   "FIELD3": "2.256",
   "FIELD4": "2.040",
   "FIELD5": "2.014",
   "FIELD6": ""
 },
 {
   "FIELD1": "Cete",
   "FIELD2": "2.284",
   "FIELD3": "2.517",
   "FIELD4": "3.113",
   "FIELD5": "3.091",
   "FIELD6": ""
 },
 {
   "FIELD1": "Cristelo",
   "FIELD2": "1.377",
   "FIELD3": "1.914",
   "FIELD4": "1.891",
   "FIELD5": "1.761",
   "FIELD6": ""
 },
 {
   "FIELD1": "Duas Igrejas",
   "FIELD2": "3.632",
   "FIELD3": "3.843",
   "FIELD4": "3.879",
   "FIELD5": "3.649",
   "FIELD6": ""
 },
 {
   "FIELD1": "Gandra",
   "FIELD2": "5.164",
   "FIELD3": "5.804",
   "FIELD4": "6.974",
   "FIELD5": "6.967",
   "FIELD6": ""
 },
 {
   "FIELD1": "Lordelo",
   "FIELD2": "9.686",
   "FIELD3": "9.930",
   "FIELD4": "10.025",
   "FIELD5": "9.107",
   "FIELD6": ""
 },
 {
   "FIELD1": "Louredo",
   "FIELD2": "1.296",
   "FIELD3": "1.364",
   "FIELD4": "1.514",
   "FIELD5": "1.384",
   "FIELD6": ""
 },
 {
   "FIELD1": "Parada de Todeia",
   "FIELD2": "1.687",
   "FIELD3": "1.844",
   "FIELD4": "1.848",
   "FIELD5": "1.793",
   "FIELD6": ""
 },
 {
   "FIELD1": "Paredes",
   "FIELD2": "",
   "FIELD3": "",
   "FIELD4": "19.834",
   "FIELD5": "20.591",
   "FIELD6": ""
 },
 {
   "FIELD1": "Rebordosa",
   "FIELD2": "9.104",
   "FIELD3": "10.813",
   "FIELD4": "9.106",
   "FIELD5": "8.496",
   "FIELD6": ""
 },
 {
   "FIELD1": "Recarei",
   "FIELD2": "4.553",
   "FIELD3": "4.686",
   "FIELD4": "4.631",
   "FIELD5": "4.479",
   "FIELD6": ""
 },
 {
   "FIELD1": "Sobreira",
   "FIELD2": "3.706",
   "FIELD3": "4.0769",
   "FIELD4": "4.300",
   "FIELD5": "4.124",
   "FIELD6": ""
 },
 {
   "FIELD1": "Sobrosa",
   "FIELD2": "2.389",
   "FIELD3": "2.502",
   "FIELD4": "2.641",
   "FIELD5": "2.497",
   "FIELD6": ""
 },
 {
   "FIELD1": "Vandoma",
   "FIELD2": "1.960",
   "FIELD3": "2.074",
   "FIELD4": "2.363",
   "FIELD5": "2.306",
   "FIELD6": ""
 },
 {
   "FIELD1": "Vilela",
   "FIELD2": "3.966",
   "FIELD3": "5.080",
   "FIELD4": "5.160",
   "FIELD5": "4.739",
   "FIELD6": ""
 },
 {
   "FIELD1": "Porto",
   "FIELD2": "Concelho",
   "FIELD3": "302.472",
   "FIELD4": "263.131",
   "FIELD5": "237.591",
   "FIELD6": "231.828"
 },
 {
   "FIELD1": "",
   "FIELD2": "Bonfim",
   "FIELD3": "34.497",
   "FIELD4": "28.578",
   "FIELD5": "24.265",
   "FIELD6": "22.981"
 },
 {
   "FIELD1": "Campanhã",
   "FIELD2": "49.107",
   "FIELD3": "38.757",
   "FIELD4": "32.659",
   "FIELD5": "29.674",
   "FIELD6": ""
 },
 {
   "FIELD1": "Paranhos",
   "FIELD2": "50.906",
   "FIELD3": "48.686",
   "FIELD4": "44.298",
   "FIELD5": "45.890",
   "FIELD6": ""
 },
 {
   "FIELD1": "Ramalde",
   "FIELD2": "36.300",
   "FIELD3": "37.647",
   "FIELD4": "38.012",
   "FIELD5": "38.849",
   "FIELD6": ""
 },
 {
   "FIELD1": "U.F. de Aldoar, Foz do Douro e Nevogilde",
   "FIELD2": "",
   "FIELD3": "",
   "FIELD4": "28.858",
   "FIELD5": "29.087",
   "FIELD6": ""
 },
 {
   "FIELD1": "U.F. de Cedofeita, Santo Ildefonso, Sé, Miragaia, São Nicolau e Vitória",
   "FIELD2": "",
   "FIELD3": "",
   "FIELD4": "40.440",
   "FIELD5": "37.434",
   "FIELD6": ""
 },
 {
   "FIELD1": "U.F. de Lordelo do Ouro e Massarelos",
   "FIELD2": "",
   "FIELD3": "",
   "FIELD4": "29.059",
   "FIELD5": "27.913",
   "FIELD6": ""
 },
 {
   "FIELD1": "Póvoa de Varzim",
   "FIELD2": "Concelho",
   "FIELD3": "302.472",
   "FIELD4": "263.131",
   "FIELD5": "237.591",
   "FIELD6": "64.257"
 },
 {
   "FIELD1": "",
   "FIELD2": "Balazar",
   "FIELD3": "2.337",
   "FIELD4": "2.475",
   "FIELD5": "2.543",
   "FIELD6": "2.482"
 },
 {
   "FIELD1": "Estela",
   "FIELD2": "2.399",
   "FIELD3": "2.596",
   "FIELD4": "2.307",
   "FIELD5": "2.287",
   "FIELD6": ""
 },
 {
   "FIELD1": "Laundos",
   "FIELD2": "2.119",
   "FIELD3": "2.131",
   "FIELD4": "2.055",
   "FIELD5": "1.937",
   "FIELD6": ""
 },
 {
   "FIELD1": "Rates",
   "FIELD2": "2.347",
   "FIELD3": "2.539",
   "FIELD4": "2.505",
   "FIELD5": "2.472",
   "FIELD6": ""
 },
 {
   "FIELD1": "U.F. da Póvoa de Varzim, Beiriz e Argivai",
   "FIELD2": "",
   "FIELD3": "",
   "FIELD4": "34.266",
   "FIELD5": "35.437",
   "FIELD6": ""
 },
 {
   "FIELD1": "U.F. de Aguçadoura e Navais",
   "FIELD2": "",
   "FIELD3": "",
   "FIELD4": "5.745",
   "FIELD5": "5.389",
   "FIELD6": ""
 },
 {
   "FIELD1": "U.F. de Aver-o-Mar, Amorim e Terroso",
   "FIELD2": "",
   "FIELD3": "",
   "FIELD4": "13.987",
   "FIELD5": "14.253",
   "FIELD6": ""
 },
 {
   "FIELD1": "Santa Maria da Feira",
   "FIELD2": "Concelho",
   "FIELD3": "118.641",
   "FIELD4": "135.964",
   "FIELD5": "139.309",
   "FIELD6": "137.615"
 },
 {
   "FIELD1": "",
   "FIELD2": "Argoncilhe",
   "FIELD3": "8.318",
   "FIELD4": "8.605",
   "FIELD5": "8.420",
   "FIELD6": "8.184"
 },
 {
   "FIELD1": "Arrifana",
   "FIELD2": "5.600",
   "FIELD3": "6.544",
   "FIELD4": "6.551",
   "FIELD5": "6.311",
   "FIELD6": ""
 },
 {
   "FIELD1": "Escapães",
   "FIELD2": "2.979",
   "FIELD3": "3.028",
   "FIELD4": "3.309",
   "FIELD5": "3.316",
   "FIELD6": ""
 },
 {
   "FIELD1": "Fiães",
   "FIELD2": "8.842",
   "FIELD3": "8.754",
   "FIELD4": "7.991",
   "FIELD5": "7.097",
   "FIELD6": ""
 },
 {
   "FIELD1": "Fornos",
   "FIELD2": "2.536",
   "FIELD3": "2.810",
   "FIELD4": "3.397",
   "FIELD5": "3.436",
   "FIELD6": ""
 },
 {
   "FIELD1": "Lourosa",
   "FIELD2": "8.113",
   "FIELD3": "9.204",
   "FIELD4": "8.636",
   "FIELD5": "8.005",
   "FIELD6": ""
 },
 {
   "FIELD1": "Milheirós de Poiares",
   "FIELD2": "2.823",
   "FIELD3": "3.859",
   "FIELD4": "3.791",
   "FIELD5": "3.594",
   "FIELD6": ""
 },
 {
   "FIELD1": "Mozelos",
   "FIELD2": "4.800",
   "FIELD3": "6.502",
   "FIELD4": "7.142",
   "FIELD5": "7.297",
   "FIELD6": ""
 },
 {
   "FIELD1": "Nogueira da Regedoura",
   "FIELD2": "4.259",
   "FIELD3": "5.026",
   "FIELD4": "5.790",
   "FIELD5": "5.740",
   "FIELD6": ""
 },
 {
   "FIELD1": "Paços de Brandão",
   "FIELD2": "4.469",
   "FIELD3": "4.590",
   "FIELD4": "4.867",
   "FIELD5": "4.775",
   "FIELD6": ""
 },
 {
   "FIELD1": "Rio Meão",
   "FIELD2": "4.324",
   "FIELD3": "4.688",
   "FIELD4": "4.931",
   "FIELD5": "4.814",
   "FIELD6": ""
 },
 {
   "FIELD1": "Romariz",
   "FIELD2": "3.358",
   "FIELD3": "3.650",
   "FIELD4": "3.023",
   "FIELD5": "2.739",
   "FIELD6": ""
 },
 {
   "FIELD1": "Sanguedo",
   "FIELD2": "3.154",
   "FIELD3": "3.542",
   "FIELD4": "3.600",
   "FIELD5": "3.475",
   "FIELD6": ""
 },
 {
   "FIELD1": "Santa Maria de Lamas",
   "FIELD2": "3.900",
   "FIELD3": "5.120",
   "FIELD4": "5.073",
   "FIELD5": "4.748",
   "FIELD6": ""
 },
 {
   "FIELD1": "São João de Ver",
   "FIELD2": "6.981",
   "FIELD3": "8.816",
   "FIELD4": "10.579",
   "FIELD5": "11.029",
   "FIELD6": ""
 },
 {
   "FIELD1": "São Paio de Oleiros",
   "FIELD2": "3.682",
   "FIELD3": "4.003",
   "FIELD4": "4.069",
   "FIELD5": "3.661",
   "FIELD6": ""
 },
 {
   "FIELD1": "U.F. de Caldas de São Jorge e Pigeiros",
   "FIELD2": "",
   "FIELD3": "",
   "FIELD4": "3.897",
   "FIELD5": "3.689",
   "FIELD6": ""
 },
 {
   "FIELD1": "U.F. de Canedo, Vale e Vila Maior",
   "FIELD2": "",
   "FIELD3": "",
   "FIELD4": "9.455",
   "FIELD5": "8.882",
   "FIELD6": ""
 },
 {
   "FIELD1": "U.F. de Lobão, Gião, Louredo e Guisande",
   "FIELD2": "",
   "FIELD3": "",
   "FIELD4": "9.860",
   "FIELD5": "9.649",
   "FIELD6": ""
 },
 {
   "FIELD1": "U.F. de Santa Maria da Feira, Travanca, Sanfins e Espargo",
   "FIELD2": "",
   "FIELD3": "",
   "FIELD4": "18.194",
   "FIELD5": "19.792",
   "FIELD6": ""
 },
 {
   "FIELD1": "U.F. de São Miguel de Souto e Mosteirô",
   "FIELD2": "",
   "FIELD3": "",
   "FIELD4": "6.734",
   "FIELD5": "6.482",
   "FIELD6": ""
 },
 {
   "FIELD1": "Santo Tirso",
   "FIELD2": "Concelho",
   "FIELD3": "69.773",
   "FIELD4": "72.396",
   "FIELD5": "71.530",
   "FIELD6": "67.725"
 },
 {
   "FIELD1": "",
   "FIELD2": "Agrela",
   "FIELD3": "1.581",
   "FIELD4": "1.604",
   "FIELD5": "1.584",
   "FIELD6": "1.486"
 },
 {
   "FIELD1": "Água Longa",
   "FIELD2": "1.968",
   "FIELD3": "2.134",
   "FIELD4": "2.207",
   "FIELD5": "2.342",
   "FIELD6": ""
 },
 {
   "FIELD1": "Aves",
   "FIELD2": "8.485",
   "FIELD3": "8.492",
   "FIELD4": "8.458",
   "FIELD5": "7.948",
   "FIELD6": ""
 },
 {
   "FIELD1": "Monte Córdova",
   "FIELD2": "3.122",
   "FIELD3": "3.669",
   "FIELD4": "3.958",
   "FIELD5": "3.850",
   "FIELD6": ""
 },
 {
   "FIELD1": "Negrelos (São Tomé)",
   "FIELD2": "4.169",
   "FIELD3": "4.241",
   "FIELD4": "4.032",
   "FIELD5": "3.755",
   "FIELD6": ""
 },
 {
   "FIELD1": "Rebordões",
   "FIELD2": "3.744",
   "FIELD3": "3.559",
   "FIELD4": "3.368",
   "FIELD5": "3.130",
   "FIELD6": ""
 },
 {
   "FIELD1": "Reguenga",
   "FIELD2": "1.480",
   "FIELD3": "1.595",
   "FIELD4": "1.596",
   "FIELD5": "1.427",
   "FIELD6": ""
 },
 {
   "FIELD1": "Roriz",
   "FIELD2": "3.978",
   "FIELD3": "3.724",
   "FIELD4": "3.665",
   "FIELD5": "3.308",
   "FIELD6": ""
 },
 {
   "FIELD1": "U.F. de Areias, Sequeiró, Lama e Palmeira",
   "FIELD2": "",
   "FIELD3": "",
   "FIELD4": "6.795",
   "FIELD5": "6.369",
   "FIELD6": ""
 },
 {
   "FIELD1": "U.F. de Carreira e Refojos de Riba de Ave",
   "FIELD2": "",
   "FIELD3": "",
   "FIELD4": "2.072",
   "FIELD5": "2.042",
   "FIELD6": ""
 },
 {
   "FIELD1": "U.F. de Lamelas e Guimarei",
   "FIELD2": "",
   "FIELD3": "",
   "FIELD4": "1.660",
   "FIELD5": "1.567",
   "FIELD6": ""
 },
 {
   "FIELD1": "U.F. de Santo Tirso, Couto (Santa Cristina e São Miguel) e Burgães",
   "FIELD2": "",
   "FIELD3": "",
   "FIELD4": "21.538",
   "FIELD5": "20.595",
   "FIELD6": ""
 },
 {
   "FIELD1": "Vila Nova do Campo",
   "FIELD2": "",
   "FIELD3": "",
   "FIELD4": "6.809",
   "FIELD5": "6.315",
   "FIELD6": ""
 },
 {
   "FIELD1": "Vilarinho",
   "FIELD2": "3.674",
   "FIELD3": "4.036",
   "FIELD4": "3.788",
   "FIELD5": "3.591",
   "FIELD6": ""
 },
 {
   "FIELD1": "São João da Madeira",
   "FIELD2": "Concelho",
   "FIELD3": "18.452",
   "FIELD4": "21.102",
   "FIELD5": "21.713",
   "FIELD6": "22.144"
 },
 {
   "FIELD1": "",
   "FIELD2": "São João da Madeira",
   "FIELD3": "18.452",
   "FIELD4": "21.102",
   "FIELD5": "21.713",
   "FIELD6": "22.144"
 },
 {
   "FIELD1": "Trofa",
   "FIELD2": "Concelho",
   "FIELD3": "32.820",
   "FIELD4": "37.581",
   "FIELD5": "38.999",
   "FIELD6": "38.554"
 },
 {
   "FIELD1": "",
   "FIELD2": "Covelas",
   "FIELD3": "1.560",
   "FIELD4": "1.662",
   "FIELD5": "1.563",
   "FIELD6": "1.463"
 },
 {
   "FIELD1": "Muro",
   "FIELD2": "1.356",
   "FIELD3": "1.972",
   "FIELD4": "1.922",
   "FIELD5": "1.840",
   "FIELD6": ""
 },
 {
   "FIELD1": "U.F. de Alvarelhos e Guidões",
   "FIELD2": "",
   "FIELD3": "",
   "FIELD4": "4.810",
   "FIELD5": "4.771",
   "FIELD6": ""
 },
 {
   "FIELD1": "U.F. de Bougado (São Martinho e Santiago)",
   "FIELD2": "",
   "FIELD3": "",
   "FIELD4": "21.585",
   "FIELD5": "21.375",
   "FIELD6": ""
 },
 {
   "FIELD1": "U.F. de Coronado (São Romão e São Mamede)",
   "FIELD2": "",
   "FIELD3": "",
   "FIELD4": "9.119",
   "FIELD5": "9.105",
   "FIELD6": ""
 },
 {
   "FIELD1": "Vale de Cambra",
   "FIELD2": "Concelho",
   "FIELD3": "24.537",
   "FIELD4": "24.798",
   "FIELD5": "22.864",
   "FIELD6": "21.275"
 },
 {
   "FIELD1": "",
   "FIELD2": "Arões",
   "FIELD3": "2.202",
   "FIELD4": "1.952",
   "FIELD5": "1.459",
   "FIELD6": "1.169"
 },
 {
   "FIELD1": "Cepelos",
   "FIELD2": "1.759",
   "FIELD3": "1.587",
   "FIELD4": "1.313",
   "FIELD5": "1.158",
   "FIELD6": ""
 },
 {
   "FIELD1": "Junqueira",
   "FIELD2": "1.466",
   "FIELD3": "1.295",
   "FIELD4": "1.067",
   "FIELD5": "834",
   "FIELD6": ""
 },
 {
   "FIELD1": "Macieira de Cambra",
   "FIELD2": "4.704",
   "FIELD3": "4.821",
   "FIELD4": "4.747",
   "FIELD5": "4.391",
   "FIELD6": ""
 },
 {
   "FIELD1": "Roge",
   "FIELD2": "1.933",
   "FIELD3": "1.901",
   "FIELD4": "1.752",
   "FIELD5": "1.540",
   "FIELD6": ""
 },
 {
   "FIELD1": "São Pedro de Castelões",
   "FIELD2": "7.389",
   "FIELD3": "7.625",
   "FIELD4": "7.181",
   "FIELD5": "6.833",
   "FIELD6": ""
 },
 {
   "FIELD1": "U.F. de Vila Chã, Codal e Vila Cova de Perrinho",
   "FIELD2": "",
   "FIELD3": "",
   "FIELD4": "5.345",
   "FIELD5": "5.350",
   "FIELD6": ""
 },
 {
   "FIELD1": "Valongo",
   "FIELD2": "Concelho",
   "FIELD3": "74.172",
   "FIELD4": "86.005",
   "FIELD5": "93.858",
   "FIELD6": "94.697"
 },
 {
   "FIELD1": "",
   "FIELD2": "Alfena",
   "FIELD3": "12.129",
   "FIELD4": "13.665",
   "FIELD5": "15.211",
   "FIELD6": "14.439"
 },
 {
   "FIELD1": "Ermesinde",
   "FIELD2": "34.415",
   "FIELD3": "38.315",
   "FIELD4": "38.798",
   "FIELD5": "39.095",
   "FIELD6": ""
 },
 {
   "FIELD1": "U.F de Campo e Sobrado",
   "FIELD2": "",
   "FIELD3": "",
   "FIELD4": "15.924",
   "FIELD5": "15.280",
   "FIELD6": ""
 },
 {
   "FIELD1": "Valongo",
   "FIELD2": "13.103",
   "FIELD3": "18.698",
   "FIELD4": "23.925",
   "FIELD5": "25.883",
   "FIELD6": ""
 },
 {
   "FIELD1": "Vila do Conde",
   "FIELD2": "Concelho",
   "FIELD3": "64.836",
   "FIELD4": "74.391",
   "FIELD5": "79.533",
   "FIELD6": "80.831"
 },
 {
   "FIELD1": "",
   "FIELD2": "Árvore",
   "FIELD3": "3.406",
   "FIELD4": "4.261",
   "FIELD5": "5.196",
   "FIELD6": "5.569"
 },
 {
   "FIELD1": "Aveleda",
   "FIELD2": "1.446",
   "FIELD3": "1.479",
   "FIELD4": "1.314",
   "FIELD5": "1.224",
   "FIELD6": ""
 },
 {
   "FIELD1": "Azurara",
   "FIELD2": "1.794",
   "FIELD3": "2.102",
   "FIELD4": "2.305",
   "FIELD5": "2.367",
   "FIELD6": ""
 },
 {
   "FIELD1": "Fajozes",
   "FIELD2": "1.457",
   "FIELD3": "1.467",
   "FIELD4": "1.425",
   "FIELD5": "1.637",
   "FIELD6": ""
 },
 {
   "FIELD1": "Gião",
   "FIELD2": "1.457",
   "FIELD3": "1.535",
   "FIELD4": "1.756",
   "FIELD5": "1.659",
   "FIELD6": ""
 },
 {
   "FIELD1": "Guilhabreu",
   "FIELD2": "1.885",
   "FIELD3": "2.386",
   "FIELD4": "2.357",
   "FIELD5": "2.190",
   "FIELD6": ""
 },
 {
   "FIELD1": "Junqueira",
   "FIELD2": "1.929",
   "FIELD3": "2.234",
   "FIELD4": "2.019",
   "FIELD5": "1.917",
   "FIELD6": ""
 },
 {
   "FIELD1": "Labruge",
   "FIELD2": "2.159",
   "FIELD3": "2.472",
   "FIELD4": "2.806",
   "FIELD5": "3.000",
   "FIELD6": ""
 },
 {
   "FIELD1": "Macieira da Maia",
   "FIELD2": "1.870",
   "FIELD3": "1.898",
   "FIELD4": "2.321",
   "FIELD5": "2.491",
   "FIELD6": ""
 },
 {
   "FIELD1": "Mindelo",
   "FIELD2": "2.859",
   "FIELD3": "3.402",
   "FIELD4": "3.491",
   "FIELD5": "3.988",
   "FIELD6": ""
 },
 {
   "FIELD1": "Modivas",
   "FIELD2": "1.888",
   "FIELD3": "1.899",
   "FIELD4": "1.806",
   "FIELD5": "1.764",
   "FIELD6": ""
 },
 {
   "FIELD1": "U.F. de Bagunte, Ferreiró, Outeiro Maior e Parada",
   "FIELD2": "",
   "FIELD3": "",
   "FIELD4": "2.848",
   "FIELD5": "2.662",
   "FIELD6": ""
 },
 {
   "FIELD1": "U.F. de Fornelo e Vairão",
   "FIELD2": "",
   "FIELD3": "",
   "FIELD4": "2.643",
   "FIELD5": "2.413",
   "FIELD6": ""
 },
 {
   "FIELD1": "U.F. de Malta e Canidelo",
   "FIELD2": "",
   "FIELD3": "",
   "FIELD4": "2.291",
   "FIELD5": "2.221",
   "FIELD6": ""
 },
 {
   "FIELD1": "U.F. de Retorta e Tougues",
   "FIELD2": "",
   "FIELD3": "",
   "FIELD4": "2.052",
   "FIELD5": "2.044",
   "FIELD6": ""
 },
 {
   "FIELD1": "U.F. de Rio Mau e Arcos",
   "FIELD2": "",
   "FIELD3": "",
   "FIELD4": "2.681",
   "FIELD5": "2.643",
   "FIELD6": ""
 },
 {
   "FIELD1": "U.F. de Touguinha e Touguinhó",
   "FIELD2": "",
   "FIELD3": "",
   "FIELD4": "3.386",
   "FIELD5": "3.346",
   "FIELD6": ""
 },
 {
   "FIELD1": "U.F. de Vilar e Mosteiró",
   "FIELD2": "",
   "FIELD3": "",
   "FIELD4": "2.569",
   "FIELD5": "2.398",
   "FIELD6": ""
 },
 {
   "FIELD1": "Vila Chã",
   "FIELD2": "3.021",
   "FIELD3": "2.957",
   "FIELD4": "3.094",
   "FIELD5": "3.404",
   "FIELD6": ""
 },
 {
   "FIELD1": "Vila do Conde",
   "FIELD2": "19.990",
   "FIELD3": "25.731",
   "FIELD4": "28.636",
   "FIELD5": "29.332",
   "FIELD6": ""
 },
 {
   "FIELD1": "Vilar de Pinheiro",
   "FIELD2": "2.269",
   "FIELD3": "2.579",
   "FIELD4": "2.537",
   "FIELD5": "2.562",
   "FIELD6": ""
 },
 {
   "FIELD1": "Vila Nova de Gaia",
   "FIELD2": "Concelho",
   "FIELD3": "248.565",
   "FIELD4": "288.749",
   "FIELD5": "302.298",
   "FIELD6": "303.854"
 },
 {
   "FIELD1": "",
   "FIELD2": "Arcozelo",
   "FIELD3": "9.610",
   "FIELD4": "12.393",
   "FIELD5": "14.352",
   "FIELD6": "15.145"
 },
 {
   "FIELD1": "Avintes",
   "FIELD2": "10.986",
   "FIELD3": "11.523",
   "FIELD4": "11.497",
   "FIELD5": "10.838",
   "FIELD6": ""
 },
 {
   "FIELD1": "Canelas",
   "FIELD2": "8.275",
   "FIELD3": "12.303",
   "FIELD4": "13.459",
   "FIELD5": "13.919",
   "FIELD6": ""
 },
 {
   "FIELD1": "Canidelo",
   "FIELD2": "16.987",
   "FIELD3": "23.737",
   "FIELD4": "27.769",
   "FIELD5": "28.059",
   "FIELD6": ""
 },
 {
   "FIELD1": "Madalena",
   "FIELD2": "8.597",
   "FIELD3": "9.356",
   "FIELD4": "10.040",
   "FIELD5": "10.553",
   "FIELD6": ""
 },
 {
   "FIELD1": "Oliveira do Douro",
   "FIELD2": "20.645",
   "FIELD3": "23.384",
   "FIELD4": "22.383",
   "FIELD5": "22.616",
   "FIELD6": ""
 },
 {
   "FIELD1": "São Félix da Marinha",
   "FIELD2": "9.816",
   "FIELD3": "11.171",
   "FIELD4": "12.706",
   "FIELD5": "13.560",
   "FIELD6": ""
 },
 {
   "FIELD1": "U.F. de Grijó e Sermonde",
   "FIELD2": "",
   "FIELD3": "",
   "FIELD4": "11.938",
   "FIELD5": "12.018",
   "FIELD6": ""
 },
 {
   "FIELD1": "U.F. de Gulpilhares e Valadares",
   "FIELD2": "",
   "FIELD3": "",
   "FIELD4": "22.019",
   "FIELD5": "22.324",
   "FIELD6": ""
 },
 {
   "FIELD1": "U.F. de Mafamude e Vilar do Paraíso",
   "FIELD2": "",
   "FIELD3": "",
   "FIELD4": "52.422",
   "FIELD5": "52.850",
   "FIELD6": ""
 },
 {
   "FIELD1": "U.F. de Pedroso e Seixezelo",
   "FIELD2": "",
   "FIELD3": "",
   "FIELD4": "20.426",
   "FIELD5": "20.229",
   "FIELD6": ""
 },
 {
   "FIELD1": "U.F. de Sandim, Olival, Lever e Crestuma",
   "FIELD2": "",
   "FIELD3": "",
   "FIELD4": "17.168",
   "FIELD5": "15.956",
   "FIELD6": ""
 },
 {
   "FIELD1": "U.F. de Santa Marinha e São Pedro da Afurada",
   "FIELD2": "",
   "FIELD3": "",
   "FIELD4": "33.714",
   "FIELD5": "34.035",
   "FIELD6": ""
 },
 {
   "FIELD1": "U.F. de Serzedo e Perosinho",
   "FIELD2": "",
   "FIELD3": "",
   "FIELD4": "14.250",
   "FIELD5": "13.746",
   "FIELD6": ""
 },
 {
   "FIELD1": "Vilar de Andorinho",
   "FIELD2": "11.518",
   "FIELD3": "16.710",
   "FIELD4": "18.155",
   "FIELD5": "18.006",
   "FIELD6": ""
 }
]